pyproject.toml
setup.py
gop/__init__.py
gop.egg-info/PKG-INFO
gop.egg-info/SOURCES.txt
gop.egg-info/dependency_links.txt
gop.egg-info/top_level.txt