Metadata-Version: 2.1
Name: gop
Version: 0.1
Summary: pip alternative (named)
Author-email: AWeirdDev <aweirdscratcher@gmail.com>
Project-URL: Homepage, https://github.com/AWeirdScratcher/gop
Project-URL: Bug Tracker, https://github.com/AWeirdScratcher/gop/issues
Keywords: gop
Classifier: Programming Language :: Python :: 3
Classifier: License :: OSI Approved :: MIT License
Classifier: Operating System :: OS Independent
Requires-Python: >=3
